target_mysql/__init__.py
target_mysql/sinks.py
target_mysql/target.py
target_mysql/tests/__init__.py
target_mysql/tests/data_files/array_data.singer
target_mysql/tests/data_files/camelcase.singer
target_mysql/tests/data_files/camelcase_complex_schema.singer
target_mysql/tests/data_files/duplicate_records.singer
target_mysql/tests/data_files/encoded_strings.singer
target_mysql/tests/data_files/illegal_colnames.singer
target_mysql/tests/data_files/integer_null_value.singer
target_mysql/tests/data_files/invalid_schema.singer
target_mysql/tests/data_files/large_int.singer
target_mysql/tests/data_files/missing_value.singer
target_mysql/tests/data_files/multiple_state_messages.singer
target_mysql/tests/data_files/no_primary_keys.singer
target_mysql/tests/data_files/no_primary_keys_append.singer
target_mysql/tests/data_files/numerics.singer
target_mysql/tests/data_files/optional_attributes.singer
target_mysql/tests/data_files/record_before_schema.singer
target_mysql/tests/data_files/record_missing_key_property.singer
target_mysql/tests/data_files/record_missing_required_property.singer
target_mysql/tests/data_files/schema_no_properties.singer
target_mysql/tests/data_files/schema_updates.singer
target_mysql/tests/data_files/special_chars_in_attributes.singer
target_mysql/tests/data_files/string_null_value.singer
target_mysql/tests/data_files/tap_aapl.singer
target_mysql/tests/data_files/target_schema.singer
target_mysql/tests/data_files/update_records.singer
target_mysql/tests/data_files/user_location_data.singer
target_mysql/tests/data_files/user_location_upsert_data.singer
target_mysql/tests/test_core.py
thk_target_mysql-0.1.3.dist-info/entry_points.txt
thk_target_mysql-0.1.3.dist-info/LICENSE
thk_target_mysql-0.1.3.dist-info/METADATA
thk_target_mysql-0.1.3.dist-info/WHEEL
thk_target_mysql-0.1.3.dist-info/RECORD
