Metadata-Version: 2.1
Name: thk-target-mysql
Version: 0.1.3
Summary: `target-mysql` is a Singer target for MySQL, built with the Meltano Singer SDK.
Home-page: https://github.com/thkwag/target-mysql
License: Apache 2.0
Keywords: ELT,MySQL,Singer,Meltano
Author: Taehwan Kwag
Author-email: thkwag@gmail.com
Requires-Python: >=3.8.1,<=3.11
Classifier: License :: Other/Proprietary License
Classifier: Programming Language :: Python :: 3
Classifier: Programming Language :: Python :: 3.9
Classifier: Programming Language :: Python :: 3.10
Classifier: Programming Language :: Python :: 3.11
Requires-Dist: cryptography (>=41.0.2,<42.0.0)
Requires-Dist: mysqlclient (>=2.2.0,<3.0.0)
Requires-Dist: requests (>=2.25.1,<3.0.0)
Requires-Dist: singer-sdk (>=0.30.0,<0.31.0)
Project-URL: Repository, https://github.com/thkwag/target-mysql
